webopen/__init__.py
webopen/main.py
webopen-0.1.0.dist-info/METADATA
webopen-0.1.0.dist-info/WHEEL
webopen-0.1.0.dist-info/licenses/LICENSE.txt
webopen-0.1.0.dist-info/RECORD
