Metadata-Version: 2.3
Name: webopen
Version: 0.1.0
Summary: A small example package
Project-URL: Homepage, https://github.com/BhuvaneshwarMarri/webopen
Project-URL: Issues, https://github.com/BhuvaneshwarMarri/webopen/issues
Author-email: Bhuvaneshwar_Marri <bhuvaneshwarmarri@gmail.com>
License-File: LICENSE.txt
Classifier: License :: OSI Approved :: MIT License
Classifier: Operating System :: OS Independent
Classifier: Programming Language :: Python :: 3
Requires-Python: >=3.8
